dkjason/__init__.py
dkjason/jason.py
dkjason-3.0.6.dist-info/LICENSE
dkjason-3.0.6.dist-info/METADATA
dkjason-3.0.6.dist-info/WHEEL
dkjason-3.0.6.dist-info/top_level.txt
dkjason-3.0.6.dist-info/RECORD
