Metadata-Version: 2.1
Name: dkjason
Version: 3.0.6
Summary: dkjason - Helper module to send json encoded data from Python
Home-page: UNKNOWN
License: UNKNOWN
Platform: UNKNOWN
Classifier: Development Status :: 5 - Production/Stable
Classifier: Intended Audience :: Developers
Classifier: Programming Language :: Python
Classifier: Programming Language :: Python :: 3
Classifier: Topic :: Software Development :: Libraries
License-File: LICENSE
Requires-Dist: Django
Requires-Dist: ttcal
